{
  "parent": "minecraft:recipes/root",
  "rewards": {
    "recipes": [
      "swdm:medium_stone_slab"
    ]
  },
  "criteria": {
    "stone": {
      "trigger": "minecraft:inventory_changed",
      "conditions": {
        "items": [
          {
            "item": "swdm:medium_stone"
          }
        ]
      }
    },
    "has_the_recipe": {
      "trigger": "minecraft:recipe_unlocked",
      "conditions": {
        "recipe": "swdm:medium_stone_slab"
      }
    }
  },
  "requirements": [
    [
      "stone",
      "has_the_recipe"
    ]
  ]
}