{
  "parent": "minecraft:recipes/root",
  "rewards": {
    "recipes": [
      "swdm:yellow_terracotta_button"
    ]
  },
  "criteria": {
    "has_stone": {
      "trigger": "minecraft:inventory_changed",
      "conditions": {
        "items": [
          {
            "item": "minecraft:yellow_terracotta"
          }
        ]
      }
    },
    "has_the_recipe": {
      "trigger": "minecraft:recipe_unlocked",
      "conditions": {
        "recipe": "swdm:yellow_terracotta_button"
      }
    }
  },
  "requirements": [
    [
      "has_stone",
      "has_the_recipe"
    ]
  ]
}